panelforecast/__init__.py
panelforecast/data/__init__.py
panelforecast/data/loader.py
panelforecast/data/preprocessing.py
panelforecast/evaluation/__init__.py
panelforecast/evaluation/metrics.py
panelforecast/forecaster.py
panelforecast/models/__init__.py
panelforecast/models/base.py
panelforecast/models/bigru.py
panelforecast/models/bilstm.py
panelforecast/models/gru.py
panelforecast/models/lstm.py
panelforecast/training/__init__.py
panelforecast/training/trainer.py
panelforecast/utils/__init__.py
panelforecast/utils/sequence.py
panelforecast-0.2.0.dist-info/LICENSE
panelforecast-0.2.0.dist-info/METADATA
panelforecast-0.2.0.dist-info/WHEEL
panelforecast-0.2.0.dist-info/RECORD
